ohptat/__init__.py
ohptat/hisob.py
ohptat-0.1.0.dist-info/licenses/LICENSE
ohptat-0.1.0.dist-info/METADATA
ohptat-0.1.0.dist-info/WHEEL
ohptat-0.1.0.dist-info/top_level.txt
ohptat-0.1.0.dist-info/RECORD
